termlauncher/__init__.py
termlauncher/__main__.py
termlauncher/old__main__.py
termlauncher-0.1.5.dist-info/LICENSE
termlauncher-0.1.5.dist-info/METADATA
termlauncher-0.1.5.dist-info/WHEEL
termlauncher-0.1.5.dist-info/top_level.txt
termlauncher-0.1.5.dist-info/RECORD
