Metadata-Version: 2.1
Name: termlauncher
Version: 0.1.5
Summary: A Textual-based terminal launcher
Author-email: falldeaf <falldeaf@gmail.com>
Project-URL: Homepage, https://github.com/falldeaf/termlauncher
Classifier: Programming Language :: Python :: 3
Classifier: License :: OSI Approved :: MIT License
Classifier: Operating System :: OS Independent
Requires-Python: >=3.7
License-File: LICENSE
